{
  "employee": [
    {
      "name": "Parminder",
      "profileUrl": "../Assets/profile-images/Pic-1.png",
      "gender": "Female",
      "departMent": "Sales",
      "salary": "25000",
      "startDate": "7 Oct 2018",
      "notes": "Pam",
      "id": 4
    },
    {
      "name": "Amit",
      "profileUrl": "../Assets/profile-images/Pic-2.png",
      "gender": "Male",
      "departMent": "HR",
      "salary": "25000",
      "startDate": "18 Oct 2021",
      "notes": "kk",
      "id": 5
    },
    {
      "name": "Karan",
      "profileUrl": "../Assets/profile-images/Pic-3.png",
      "gender": "Male",
      "departMent": "HR",
      "salary": "30000",
      "startDate": "19 Nov 2019",
      "notes": "kk",
      "id": 6
    }
  ]
}